README.md
setup.py
buildapi/__init__.py
buildapi.egg-info/PKG-INFO
buildapi.egg-info/SOURCES.txt
buildapi.egg-info/dependency_links.txt
buildapi.egg-info/top_level.txt