Metadata-Version: 1.0
Name: buildapi
Version: 0.0.1
Summary: a library for build http api
Home-page: https://github.com/snbck/buildApi
Author: snbck
Author-email: snbckcode@gmail.com
License: Mozilla Public License 2.0
Keywords: buildapi
Platform: any
